LICENSE
MANIFEST.in
dbwrap.py
setup.py
dbwrap.egg-info/PKG-INFO
dbwrap.egg-info/SOURCES.txt
dbwrap.egg-info/dependency_links.txt
dbwrap.egg-info/top_level.txt
dbwrap.egg-info/zip-safe