Metadata-Version: 1.0
Name: dbwrap
Version: 0.3.2
Summary: a simple convenience wrapper for DB-API connections
Home-page: http://code.google.com/p/dbwrap/
Author: Pianohacker
Author-email: pianohacker@gmail.com
License: LGPL
Platform: UNKNOWN
